{
  "display": {
    "icon": {
      "item": "iceandfire:dragonsteel_fire_helmet"
    },
    "title": [
      {
        "text": "Power Ranger",
        "color": "purple",
        "bold": true
      }
    ],
    "description": "Make a full set of each type of dragonsteel.",
    "frame": "challenge",
    "show_toast": true,
    "announce_to_chat": true,
    "hidden": false
  },
  "parent": "baersadditions:other/exploration/dragonsteel_complete",
  "criteria": {
    "fire": {
      "trigger": "minecraft:inventory_changed",
      "conditions": {
        "items": [
          {
            "item": "iceandfire:dragonsteel_fire_helmet"
          },
          {
            "item": "iceandfire:dragonsteel_fire_chestplate"
          },
          {
            "item": "iceandfire:dragonsteel_fire_leggings"
          },
          {
            "item": "iceandfire:dragonsteel_fire_boots"
          }
        ]
      }
    },
    "ice": {
      "trigger": "minecraft:inventory_changed",
      "conditions": {
        "items": [
          {
            "item": "iceandfire:dragonsteel_ice_helmet"
          },
          {
            "item": "iceandfire:dragonsteel_ice_chestplate"
          },
          {
            "item": "iceandfire:dragonsteel_ice_leggings"
          },
          {
            "item": "iceandfire:dragonsteel_ice_boots"
          }
        ]
      }
    },
    "lightning": {
      "trigger": "minecraft:inventory_changed",
      "conditions": {
        "items": [
          {
            "item": "iceandfire:dragonsteel_lightning_helmet"
          },
          {
            "item": "iceandfire:dragonsteel_lightning_chestplate"
          },
          {
            "item": "iceandfire:dragonsteel_lightning_leggings"
          },
          {
            "item": "iceandfire:dragonsteel_lightning_boots"
          }
        ]
      }
    }
  },
  "requirements": [
    [
      "fire"
    ],
    [
      "ice"
    ],
    [
      "lightning"
    ]
  ]
}
