{
    "name": "Cyclops",
    "icon": "thermal:iron_coin",
    "category": "patchouli:creature_trophies",
    "pages": [
        {
            "trigger": "baersadditions:quests/collecting/heads/cyclops",
            "type": "quest",
            "text": "$(6)$(bold)Goal:$() Collect 1 cyclops skull from a cyclops. $(br2)$(6)$(bold)Where are they found?:$() Cyclops are found in beach biomes and very rarely wander in plains and savannas."
        },
        {
            "type": "entity",
            "entity": "iceandfire:cyclops{Variant: 0}",
            "text": "Bald variant",
            "offset": 0.6
        },
        {
            "type": "entity",
            "entity": "iceandfire:cyclops{Variant: 1}",
            "text": "Long-bearded variant",
            "offset": 0.6
        },
        {
            "type": "entity",
            "entity": "iceandfire:cyclops{Variant: 2}",
            "text": "Bearded variant",
            "offset": 0.6
        },
        {
            "type": "entity",
            "entity": "iceandfire:cyclops{Variant: 3}",
            "text": "Hairy variant",
            "offset": 0.6
        }
    ],
    "turnin": "baersadditions:quests/collecting/heads/cyclops"
}